pytorch2caffe/__init__.py
pytorch2caffe/caffe_net.py
pytorch2caffe/caffe_pb2.py
pytorch2caffe/layer_param.py
pytorch2caffe/pytorch2caffe.py
pytorch2caffe-0.1.0.dist-info/DESCRIPTION.rst
pytorch2caffe-0.1.0.dist-info/METADATA
pytorch2caffe-0.1.0.dist-info/RECORD
pytorch2caffe-0.1.0.dist-info/WHEEL
pytorch2caffe-0.1.0.dist-info/metadata.json
pytorch2caffe-0.1.0.dist-info/top_level.txt
