Metadata-Version: 2.0
Name: pytorch2caffe
Version: 0.1.0
Summary: A package to convert pytorch model to caffe model
Home-page: https://github.com/woodsgao/pytorch2caffe
Author: woodsgao
Author-email: woodsgao@outlook.com
License: MIT
Platform: UNKNOWN
Classifier: License :: OSI Approved :: GNU General Public License v3 (GPLv3)
Classifier: Programming Language :: Python
Classifier: Programming Language :: Python :: 3
Classifier: Programming Language :: Python :: 3.5
Classifier: Programming Language :: Python :: 3.6
Classifier: Programming Language :: Python :: 3.7
Classifier: Programming Language :: Python :: Implementation :: CPython
Classifier: Programming Language :: Python :: Implementation :: PyPy
Requires-Python: >=3.5.2
Requires-Dist: numpy (>=1.11)
Requires-Dist: torch (>=1.0)
